caml/__init__.py
caml/_version.py
caml/core/__init__.py
caml/core/_base.py
caml/core/cate.py
caml/core/ols.py
caml/core/modeling/__init__.py
caml/core/modeling/model_bank.py
caml/core/modeling/score.py
caml/distributed/__init__.py
caml/distributed/ray.py
caml/extensions/__init__.py
caml/extensions/plots.py
caml/extensions/synthetic_data.py
caml/generics/__init__.py
caml/generics/decorators.py
caml/generics/interfaces.py
caml/generics/logging.py
caml/generics/monkey_patch.py
caml/generics/utils.py
caml-0.0.0.dev17.dist-info/METADATA
caml-0.0.0.dev17.dist-info/WHEEL
caml-0.0.0.dev17.dist-info/licenses/LICENSE
caml-0.0.0.dev17.dist-info/RECORD
