Metadata-Version: 2.4
Name: caml
Version: 0.0.0.dev17
Summary: Extensions & abstractions of advanced econometric techniques leveraging machine learning.
Project-URL: Homepage, https://caml-docs.com
Project-URL: Documentation, https://caml-docs.com/
Project-URL: Source Code, https://github.com/jakepenzak/caml
Project-URL: Bug Tracker, https://github.com/jakepenzak/caml/issues
Author-email: Jacob Pieniazek <jacob@pieniazek.me>
Maintainer-email: Jacob Pieniazek <jacob@pieniazek.me>
License: MIT
License-File: LICENSE
Keywords: automl,causal inference,econometrics,heterogeneity,machine learning
Classifier: Development Status :: 2 - Pre-Alpha
Classifier: License :: OSI Approved :: MIT License
Classifier: Operating System :: MacOS
Classifier: Operating System :: Microsoft :: Windows
Classifier: Operating System :: POSIX :: Linux
Classifier: Programming Language :: Python
Classifier: Programming Language :: Python :: 3.10
Classifier: Programming Language :: Python :: 3.11
Classifier: Programming Language :: Python :: 3.12
Requires-Python: >=3.10
Requires-Dist: doubleml>=0.8.0
Requires-Dist: econml>=0.16
Requires-Dist: flaml[automl]>=2.0.0
Requires-Dist: llvmlite>0.40
Requires-Dist: matplotlib>=3.9.2
Requires-Dist: patsy>=1.0.1
Requires-Dist: rich>=13.9.4
Provides-Extra: ray
Requires-Dist: ray[tune]>=2.51.1; extra == 'ray'
Provides-Extra: spark
Requires-Dist: flaml[spark]>=2.0.0; extra == 'spark'
Requires-Dist: optuna>=3.6.1; extra == 'spark'
Requires-Dist: pyspark>=3.5.2; extra == 'spark'
